gql/__init__.py
gql/enum.py
gql/execute.py
gql/federation.py
gql/middleware.py
gql/parser.py
gql/playground.py
gql/resolver.py
gql/scalar.py
gql/schema.py
gql/schema_visitor.py
gql/subscription.py
gql/utils.py
python_gql-0.2.3.dist-info/LICENSE
python_gql-0.2.3.dist-info/WHEEL
python_gql-0.2.3.dist-info/METADATA
python_gql-0.2.3.dist-info/RECORD
