Metadata-Version: 2.1
Name: python-gql
Version: 0.2.3
Summary: Python schema-first GraphQL library based on GraphQL-core
Home-page: https://github.com/syfun/python-gql
License: MIT
Author: ysun
Author-email: sunyu418@gmail.com
Requires-Python: >=3.7
Classifier: License :: OSI Approved :: MIT License
Classifier: Programming Language :: Python :: 3
Classifier: Programming Language :: Python :: 3.7
Classifier: Programming Language :: Python :: 3.8
Classifier: Programming Language :: Python :: 3.9
Requires-Dist: graphql-core (>=3,<4)
